TournamentAPI/Tournament.py
TournamentAPI/TournamentAPI.py
TournamentAPI/TournamentMatch.py
TournamentAPI/TournamentParticipant.py
TournamentAPI/__init__.py
TournamentAPI-0.2.1.dist-info/LICENSE
TournamentAPI-0.2.1.dist-info/METADATA
TournamentAPI-0.2.1.dist-info/WHEEL
TournamentAPI-0.2.1.dist-info/top_level.txt
TournamentAPI-0.2.1.dist-info/RECORD
